pyemcee/__init__.py
pyemcee/pyemcee.py
pyemcee/version.py
pyemcee-0.2.6.data/data/LICENSE
pyemcee-0.2.6.dist-info/AUTHORS.rst
pyemcee-0.2.6.dist-info/LICENSE
pyemcee-0.2.6.dist-info/METADATA
pyemcee-0.2.6.dist-info/WHEEL
pyemcee-0.2.6.dist-info/top_level.txt
pyemcee-0.2.6.dist-info/RECORD
