Metadata-Version: 2.1
Name: pyemcee
Version: 0.2.6
Summary: pyemcee: Python implementation of the affine-invariant MCMC Hammer
Home-page: https://mcfit.github.io/pyemcee/
Download-URL: https://github.com/mcfit/pyemcee
Author: Ashkbiz Danehkar
Author-email: ashkbiz.danehkar@students.mq.edu.au
License: http://www.gnu.org/licenses/gpl.html
Keywords: pyemcee,MCMC,emcee,Python,ensemble sampler,hammer
Platform: any
License-File: LICENSE
License-File: AUTHORS.rst
Requires-Dist: numpy
Requires-Dist: scipy
Requires-Dist: matplotlib
